calctree_client/__init__.py
calctree_client/client.py
vt4_client_test-0.1.10.dist-info/METADATA
vt4_client_test-0.1.10.dist-info/WHEEL
vt4_client_test-0.1.10.dist-info/top_level.txt
vt4_client_test-0.1.10.dist-info/RECORD
